alteraparser/__init__.py
alteraparser/ast.py
alteraparser/parser.py
alteraparser/bnf/__init__.py
alteraparser/bnf/grammar.py
alteraparser/codegen/__init__.py
alteraparser/codegen/generator.py
alteraparser/io/__init__.py
alteraparser/io/file_input.py
alteraparser/io/input_stream.py
alteraparser/io/output.py
alteraparser/io/string_input.py
alteraparser/syntaxgraph/__init__.py
alteraparser/syntaxgraph/abstract_vertex.py
alteraparser/syntaxgraph/clonable.py
alteraparser/syntaxgraph/dockable.py
alteraparser/syntaxgraph/final_vertex.py
alteraparser/syntaxgraph/match_finder.py
alteraparser/syntaxgraph/matcher_vertex.py
alteraparser/syntaxgraph/processor.py
alteraparser/syntaxgraph/vertex.py
alteraparser/syntaxgraph/vertex_group.py
alteraparser-1.0.1.data/scripts/altparsgen
alteraparser-1.0.1.dist-info/DESCRIPTION.rst
alteraparser-1.0.1.dist-info/METADATA
alteraparser-1.0.1.dist-info/RECORD
alteraparser-1.0.1.dist-info/WHEEL
alteraparser-1.0.1.dist-info/metadata.json
alteraparser-1.0.1.dist-info/top_level.txt
