Metadata-Version: 2.0
Name: alteraparser
Version: 1.0.1
Summary: A simple parser and grammar definition library
Home-page: UNKNOWN
Author: Thomas Bollmeier
Author-email: tbollmeier@web.de
License: MIT
Keywords: parser development
Platform: UNKNOWN
Classifier: Development Status :: 4 - Beta
Classifier: Intended Audience :: Developers
Classifier: Topic :: Software Development :: Build Tools
Classifier: License :: OSI Approved :: MIT License
Classifier: Programming Language :: Python :: 3
Classifier: Programming Language :: Python :: 3.2
Classifier: Programming Language :: Python :: 3.3
Classifier: Programming Language :: Python :: 3.4
Classifier: Programming Language :: Python :: 3.5
